Metadata-Version: 2.2
Name: pyuci
Version: 0.10.3
Summary: Python UCI bindings
Author-email: "CZ.NIC z.s.p.o" <karel.koci@nic.cz>
License:                     GNU GENERAL PUBLIC LICENSE
Project-URL: Homepage, https://gitlab.nic.cz/turris/pyuci
Classifier: Development Status :: 5 - Production/Stable
Classifier: License :: OSI Approved :: MIT License
Classifier: Operating System :: POSIX :: Linux
Classifier: Programming Language :: Python :: 3
Requires-Python: >=3.7
License-File: LICENSE
